gt4sd_trainer/hf_pl/__init__.py
gt4sd_trainer/hf_pl/argument_parser.py
gt4sd_trainer/hf_pl/cli_pl_to_hf_converter.py
gt4sd_trainer/hf_pl/cli_trainer.py
gt4sd_trainer/hf_pl/core.py
gt4sd_trainer/hf_pl/pytorch_lightning_trainer.py
gt4sd_trainer/hf_pl/datasets/__init__.py
gt4sd_trainer/hf_pl/datasets/core.py
gt4sd_trainer/hf_pl/models/__init__.py
gt4sd_trainer/hf_pl/models/core.py
gt4sd_trainer/hf_pl/tests/__init__.py
gt4sd_trainer/hf_pl/tests/lm_example.jsonl
gt4sd_trainer/hf_pl/tests/test_lm_trainer.py
gt4sd_trainer_hf_pl-1.0.0.dist-info/LICENSE
gt4sd_trainer_hf_pl-1.0.0.dist-info/METADATA
gt4sd_trainer_hf_pl-1.0.0.dist-info/WHEEL
gt4sd_trainer_hf_pl-1.0.0.dist-info/entry_points.txt
gt4sd_trainer_hf_pl-1.0.0.dist-info/top_level.txt
gt4sd_trainer_hf_pl-1.0.0.dist-info/RECORD
