Metadata-Version: 2.1
Name: gt4sd-trainer-hf-pl
Version: 1.0.0
Summary: Transformers trainer submodule of GT4SD.
Author: GT4SD team
Classifier: Operating System :: OS Independent
Classifier: Programming Language :: Python :: 3
Classifier: Programming Language :: Python :: 3.7
Classifier: Programming Language :: Python :: 3.8
Classifier: Programming Language :: Python :: 3.9
Classifier: Programming Language :: Python :: 3.10
License-File: LICENSE
Requires-Dist: charset-normalizer >=2.0
Requires-Dist: datasets >=1.11.0
Requires-Dist: importlib-metadata >=1.7.0
Requires-Dist: importlib-resources >=5.10.0
Requires-Dist: joblib >=1.1.0
Requires-Dist: numpy >=1.16.5
Requires-Dist: lightning >=2.0.0
Requires-Dist: pyyaml >=5.4.1
Requires-Dist: regex >=2.5.91
Requires-Dist: scikit-learn >=1.0.0
Requires-Dist: scipy >=1.0.0
Requires-Dist: sentencepiece >=0.1.95
Requires-Dist: tensorboard >=2.2.0
Requires-Dist: torch >=1.13.1
Requires-Dist: torchmetrics >=0.7.0
Requires-Dist: transformers >=4.22.0
Requires-Dist: typing-extensions >=3.7.4.3
Requires-Dist: wheel >=0.26
